clibroker/__init__.py
clibroker/clibroker.py
clibroker/utils.py
clibroker-2.0.3.dist-info/LICENSE
clibroker-2.0.3.dist-info/METADATA
clibroker-2.0.3.dist-info/WHEEL
clibroker-2.0.3.dist-info/top_level.txt
clibroker-2.0.3.dist-info/RECORD
