Metadata-Version: 2.1
Name: clibroker
Version: 2.0.3
Summary: "Command-line interface I/O broker with sessions for asynchronous applications."
Home-page: https://github.com/Kiruse/PyCliBroker
Author: Kiruse
Author-email: neurokiruse@outlook.com
License: MIT
Keywords: cmd,cli,console,command-line interface,asyncio,asynchronous,io
Platform: UNKNOWN
Requires-Python: >=3.6
